mettoolbox/__init__.py
mettoolbox/disaggregate.py
mettoolbox/evaplib.py
mettoolbox/indices.py
mettoolbox/meteo_utils.py
mettoolbox/meteolib.py
mettoolbox/mettoolbox.py
mettoolbox/pet.py
mettoolbox/ret.py
mettoolbox/tdew.py
mettoolbox/utils.py
mettoolbox/melodist/setup.py
mettoolbox/melodist/docs/source/conf.py
mettoolbox/melodist/melodist/__init__.py
mettoolbox/melodist/melodist/__version__.py
mettoolbox/melodist/melodist/cascade.py
mettoolbox/melodist/melodist/data_io.py
mettoolbox/melodist/melodist/humidity.py
mettoolbox/melodist/melodist/precipitation.py
mettoolbox/melodist/melodist/radiation.py
mettoolbox/melodist/melodist/station.py
mettoolbox/melodist/melodist/stationstatistics.py
mettoolbox/melodist/melodist/temperature.py
mettoolbox/melodist/melodist/wind.py
mettoolbox/melodist/melodist/util/__init__.py
mettoolbox/melodist/melodist/util/bunch.py
mettoolbox/melodist/melodist/util/util.py
mettoolbox/melodist/tests/test_humidity.py
mettoolbox/melodist/tests/test_io.py
mettoolbox/melodist/tests/test_precipitation.py
mettoolbox/melodist/tests/test_precipitation_5min.py
mettoolbox/melodist/tests/test_radiation.py
mettoolbox/melodist/tests/test_station.py
mettoolbox/melodist/tests/test_temperature.py
mettoolbox/melodist/tests/test_wind.py
mettoolbox/melodist/tests/util.py
mettoolbox/toolbox_utils/docs/conf.py
mettoolbox/toolbox_utils/src/toolbox_utils/__init__.py
mettoolbox/toolbox_utils/src/toolbox_utils/tsutils.py
mettoolbox/toolbox_utils/src/toolbox_utils/readers/__init__.py
mettoolbox/toolbox_utils/src/toolbox_utils/readers/hbn.py
mettoolbox/toolbox_utils/src/toolbox_utils/readers/plotgen.py
mettoolbox/toolbox_utils/src/toolbox_utils/readers/wdm.py
mettoolbox/toolbox_utils/tests/test_asbestfreq.py
mettoolbox/toolbox_utils/tests/test_date_slice.py
mettoolbox/toolbox_utils/tests/test_dateparse.py
mettoolbox/toolbox_utils/tests/test_extract.py
mettoolbox/toolbox_utils/tests/test_hbn.py
mettoolbox/toolbox_utils/tests/test_make_list.py
mettoolbox-6.0.6.dist-info/LICENSE.txt
mettoolbox-6.0.6.dist-info/METADATA
mettoolbox-6.0.6.dist-info/WHEEL
mettoolbox-6.0.6.dist-info/entry_points.txt
mettoolbox-6.0.6.dist-info/top_level.txt
mettoolbox-6.0.6.dist-info/RECORD
