Metadata-Version: 2.1
Name: mettoolbox
Version: 6.0.6
Summary: mettoolbox is set of command line and Python tools for the analysis and reporting of meteorological data.
Author-email: Tim Cera <tim@cerazone.net>
License: BSD-3-Clause
Project-URL: documentation, https://timcera.bitbucket.io/mettoolbox/docs/index.html#mettoolbox-documentation
Project-URL: github, https://github.com/timcera/mettoolbox
Project-URL: bitbucket, https://bitbucket.org/timcera/mettoolbox/src/main/
Keywords: time-series,cli-app,meteorology,evaporation,precipitation,climate,weather,climate-data,climate-data-analysis,climate-data-analysis-tools,temperature,humidity,wind
Classifier: Development Status :: 5 - Production/Stable
Classifier: Intended Audience :: Science/Research
Classifier: Intended Audience :: End Users/Desktop
Classifier: Intended Audience :: Developers
Classifier: Environment :: Console
Classifier: License :: OSI Approved :: BSD License
Classifier: Natural Language :: English
Classifier: Operating System :: OS Independent
Classifier: Programming Language :: Python :: 3 :: Only
Classifier: Programming Language :: Python :: 3.8
Classifier: Programming Language :: Python :: 3.9
Classifier: Programming Language :: Python :: 3.10
Classifier: Programming Language :: Python :: 3.11
Classifier: Topic :: Scientific/Engineering :: Information Analysis
Classifier: Topic :: Scientific/Engineering
Classifier: Topic :: Software Development :: Libraries :: Python Modules
Requires-Python: >=3.8
License-File: LICENSE.txt
Requires-Dist: tstoolbox
Requires-Dist: cltoolbox
Requires-Dist: numpy
Requires-Dist: solarpy
Requires-Dist: standard-precip
Requires-Dist: pydaymet
Requires-Dist: pyet
